tests/__init__.py
trueupdate/__init__.py
trueupdate/command_line.py
trueupdate-2.3.0.dist-info/LICENSE
trueupdate-2.3.0.dist-info/METADATA
trueupdate-2.3.0.dist-info/WHEEL
trueupdate-2.3.0.dist-info/entry_points.txt
trueupdate-2.3.0.dist-info/top_level.txt
trueupdate-2.3.0.dist-info/RECORD
