Metadata-Version: 2.1
Name: trueupdate
Version: 2.3.0
Summary: An Automatic and Bulk update utility for TrueNAS SCALE Apps
Home-page: https://github.com/truecharts/trueupdate
Author-email: into@truecharts.org
License: UNKNOWN
Platform: UNKNOWN
